string_catalog/__init__.py
string_catalog/__main__.py
string_catalog/appstoreconnect_cli.py
string_catalog/cli.py
string_catalog/coordinator.py
string_catalog/language.py
string_catalog/models.py
string_catalog/translator.py
string_catalog/utils.py
string_catalog/whats_new.py
string_catalog/xcstrings_cli.py
string_catalog-0.5.0.dist-info/licenses/LICENSE
string_catalog-0.5.0.dist-info/METADATA
string_catalog-0.5.0.dist-info/WHEEL
string_catalog-0.5.0.dist-info/entry_points.txt
string_catalog-0.5.0.dist-info/top_level.txt
string_catalog-0.5.0.dist-info/RECORD
