Metadata-Version: 2.4
Name: string-catalog
Version: 0.5.0
Summary: A CLI tool for translating Xcode string catalogs.
Author: PanicByte
License: Apache-2.0
Project-URL: Homepage, https://github.com/Sanster/string-catalog
Project-URL: Changelog, https://github.com/Sanster/string-catalog/releases
Project-URL: Issues, https://github.com/Sanster/string-catalog/issues
Project-URL: CI, https://github.com/Sanster/string-catalog/actions
Classifier: License :: OSI Approved :: Apache Software License
Requires-Python: >=3.8
License-File: LICENSE
Requires-Dist: authlib>=1.3.2
Requires-Dist: diskcache>=5.6.3
Requires-Dist: httpx[socks]>=0.28.1
Requires-Dist: openai>=1.58.1
Requires-Dist: pydantic>=2.10.4
Requires-Dist: rich>=13.9.4
Requires-Dist: tenacity>=9.0.0
Requires-Dist: typer>=0.15.1
Provides-Extra: test
Requires-Dist: pytest; extra == "test"
Dynamic: license-file
